wooji_database/__init__.py
wooji_database/interfaces/__init__.py
wooji_database/interfaces/presentation.py
wooji_database/interfaces/stock.py
woojicap_database-0.0.1.dist-info/LICENSE
woojicap_database-0.0.1.dist-info/METADATA
woojicap_database-0.0.1.dist-info/WHEEL
woojicap_database-0.0.1.dist-info/top_level.txt
woojicap_database-0.0.1.dist-info/RECORD
