Metadata-Version: 2.1
Name: woojicap-database
Version: 0.0.1
Summary: Database interface for WoojiCap
Home-page: UNKNOWN
License: UNKNOWN
Platform: UNKNOWN
Requires-Python: >=3.6
